Metadata-Version: 2.4
Name: sibd_pyerr
Version: 0.1.5
Summary: 선일빅데이터고등학교 파이썬 에러 한글화
Author-email: 김동철 <lhoiktn@gmail.com>
License-Expression: MIT
Requires-Python: >=3.8
